GeneralNewsScraper/BrowserContextAsync.py
GeneralNewsScraper/GNS.py
GeneralNewsScraper/parse_article.py
GeneralNewsScraper/parse_article_list.py
GeneralNewsScraper/score.py
GeneralNewsScraper/stealth.min.js
GeneralNewsScraper/utils.py
generalnewsscraper-0.2.4.dist-info/LICENSE
generalnewsscraper-0.2.4.dist-info/METADATA
generalnewsscraper-0.2.4.dist-info/WHEEL
generalnewsscraper-0.2.4.dist-info/RECORD
