Metadata-Version: 2.1
Name: GeneralNewsScraper
Version: 0.2.4
Summary: Common domestic and foreign news website data collection framework
Author: lijincheng
Author-email: 2040213136@qq.com
Requires-Python: >=3.11,<4.0
Classifier: Programming Language :: Python :: 3
Classifier: Programming Language :: Python :: 3.11
Classifier: Programming Language :: Python :: 3.12
Requires-Dist: lxml (==5.2.2)
Requires-Dist: playwright (==1.44.0)
Requires-Dist: pyspellchecker (==0.8.1)
